nys_schemas/__init__.py
nys_schemas/auth_schema.py
nys_schemas/bot_schema.py
nys_schemas/box_schema.py
nys_schemas/carrier_schema.py
nys_schemas/content_code.py
nys_schemas/events_schema.py
nys_schemas/export_enums.py
nys_schemas/export_schema.py
nys_schemas/group_by_options.py
nys_schemas/inventory_view_schema.py
nys_schemas/jira_schema.py
nys_schemas/job_schema.py
nys_schemas/load_schema.py
nys_schemas/request_schema.py
nys_schemas/requests_and_jobs_view_schema.py
nys_schemas/sku_schema.py
nys_schemas/sort_enums.py
nys_schemas/support_schema.py
nys_schemas/system_schema.py
nys_schemas/trigger_schema.py
nys_schemas/user_schema.py
nys_schemas-0.3.3.dist-info/licenses/LICENSE
nys_schemas-0.3.3.dist-info/METADATA
nys_schemas-0.3.3.dist-info/WHEEL
nys_schemas-0.3.3.dist-info/entry_points.txt
nys_schemas-0.3.3.dist-info/top_level.txt
nys_schemas-0.3.3.dist-info/RECORD
